pymschap/U32.py
pymschap/__init__.py
pymschap/des.py
pymschap/des_c.py
pymschap/des_data.py
pymschap/md4.py
pymschap/mppe.py
pymschap/mschap.py
pymschap/utils.py
pymschap-0.1.dist-info/DESCRIPTION.rst
pymschap-0.1.dist-info/METADATA
pymschap-0.1.dist-info/RECORD
pymschap-0.1.dist-info/WHEEL
pymschap-0.1.dist-info/metadata.json
pymschap-0.1.dist-info/top_level.txt
