Metadata-Version: 2.0
Name: pymschap
Version: 0.1
Summary: python mschap module
Home-page: https://github.com/talkincode/pymschap
Author: jamiesun
Author-email: jamiesun.net@gmail.com
License: LGPL
Keywords: mschap,mschapv1,mschapv2,pymschap
Platform: UNKNOWN
Classifier: Development Status :: 6 - Mature
Classifier: Intended Audience :: Developers
Classifier: Programming Language :: Python :: 2.7
Classifier: Topic :: Software Development :: Libraries :: Python Modules
